{
  "nombre": "Proyecto - Design Thinking",
  "descripcion": "Metodología de diseño centrado en el usuario para el desarrollo de proyectos tecnológicos en III Ciclo",
  "porcentaje": 30,
  "ciclo": "III",
  "etapas": {
    "inicial": {
      "nombre": "Etapa Inicial",
      "fases": ["empatizar", "definir"],
      "porcentaje": 30,
      "indicadores": {
        "empatizar": [
          {
            "descripcion": "Investiga y recopila información sobre el problema",
            "criterios": {
              "alto": "Recopila información variada y relevante de múltiples fuentes",
              "medio": "Recopila información básica de algunas fuentes",
              "bajo": "Recopila información limitada o no relevante"
            }
          },
          {
            "descripcion": "Identifica necesidades y características del usuario",
            "criterios": {
              "alto": "Crea perfiles de usuario detallados y realiza entrevistas",
              "medio": "Identifica algunas características del usuario",
              "bajo": "No identifica claramente al usuario o sus necesidades"
            }
          }
        ],
        "definir": [
          {
            "descripcion": "Sintetiza la información recopilada",
            "criterios": {
              "alto": "Organiza y sintetiza la información de manera clara y estructurada",
              "medio": "Sintetiza parcialmente la información",
              "bajo": "No sintetiza la información adecuadamente"
            }
          },
          {
            "descripcion": "Define el problema central del proyecto",
            "criterios": {
              "alto": "Define el problema de manera clara, específica y centrada en el usuario",
              "medio": "Define el problema de manera general",
              "bajo": "No define claramente el problema"
            }
          }
        ]
      }
    },
    "desarrollo": {
      "nombre": "Etapa de Desarrollo",
      "fases": ["idear", "prototipar"],
      "porcentaje": 40,
      "indicadores": {
        "idear": [
          {
            "descripcion": "Genera múltiples soluciones creativas",
            "criterios": {
              "alto": "Genera 5+ ideas diversas y creativas usando técnicas como brainstorming",
              "medio": "Genera 2-3 ideas básicas",
              "bajo": "Genera solo 1 idea o ideas no viables"
            }
          },
          {
            "descripcion": "Selecciona la mejor solución basada en criterios",
            "criterios": {
              "alto": "Evalúa las ideas con criterios claros y selecciona la más adecuada",
              "medio": "Selecciona una solución sin evaluación sistemática",
              "bajo": "No justifica la selección de la solución"
            }
          }
        ],
        "prototipar": [
          {
            "descripcion": "Desarrolla prototipo físico o digital",
            "criterios": {
              "alto": "Crea prototipo funcional que representa claramente la solución",
              "medio": "Crea prototipo básico con algunas funcionalidades",
              "bajo": "Prototipo incompleto o no representativo"
            }
          },
          {
            "descripcion": "Itera el prototipo basado en feedback inicial",
            "criterios": {
              "alto": "Realiza mejoras significativas basadas en feedback recibido",
              "medio": "Realiza algunas mejoras menores",
              "bajo": "No realiza mejoras basadas en feedback"
            }
          }
        ]
      }
    },
    "final": {
      "nombre": "Etapa Final",
      "fases": ["evaluar"],
      "porcentaje": 30,
      "indicadores": {
        "evaluar": [
          {
            "descripcion": "Prueba el prototipo con usuarios reales",
            "criterios": {
              "alto": "Realiza pruebas sistemáticas y recoge feedback de múltiples usuarios",
              "medio": "Realiza pruebas básicas con pocos usuarios",
              "bajo": "No realiza pruebas con usuarios reales"
            }
          },
          {
            "descripcion": "Analiza resultados y propone mejoras",
            "criterios": {
              "alto": "Analiza críticamente los resultados y propone mejoras específicas",
              "medio": "Analiza superficialmente y propone mejoras generales",
              "bajo": "No analiza resultados ni propone mejoras"
            }
          },
          {
            "descripcion": "Documenta el proceso completo del proyecto",
            "criterios": {
              "alto": "Documenta todo el proceso de manera clara, organizada y completa",
              "medio": "Documenta parcialmente el proceso",
              "bajo": "Documentación incompleta o desorganizada"
            }
          }
        ]
      }
    }
  },
  "criterios_evaluacion_final": {
    "originalidad": {
      "nombre": "Originalidad y Creatividad",
      "porcentaje": 20,
      "descripcion": "Innovación en la solución propuesta"
    },
    "funcionalidad": {
      "nombre": "Funcionalidad Técnica",
      "porcentaje": 30,
      "descripcion": "Correcto funcionamiento del prototipo"
    },
    "presentacion": {
      "nombre": "Presentación y Comunicación",
      "porcentaje": 20,
      "descripcion": "Claridad en la exposición del proyecto"
    },
    "proceso": {
      "nombre": "Proceso de Diseño",
      "porcentaje": 20,
      "descripcion": "Aplicación correcta del Design Thinking"
    },
    "trabajo_equipo": {
      "nombre": "Trabajo en Equipo",
      "porcentaje": 10,
      "descripcion": "Colaboración y distribución de tareas"
    }
  },
  "ejemplos_proyectos": [
    {
      "nombre": "App para control parental de dispositivos",
      "descripcion": "Aplicación móvil que ayuda a padres a gestionar el tiempo de pantalla de sus hijos",
      "tecnologias": ["App Inventor", "Diseño UI/UX", "Prototipado"]
    },
    {
      "nombre": "Sistema de riego automatizado",
      "descripcion": "Sistema que monitorea humedad del suelo y riega plantas automáticamente",
      "tecnologias": ["Arduino", "Sensores", "Programación C++"]
    },
    {
      "nombre": "Plataforma de reciclaje escolar",
      "descripcion": "Sistema para promover y gestionar el reciclaje en la institución educativa",
      "tecnologias": ["Diseño web", "Base de datos", "Programación"]
    }
  ]
}
